pysigrok_logic2.py
pysigrok_saleae_logic2-0.0.2.dist-info/entry_points.txt
pysigrok_saleae_logic2-0.0.2.dist-info/LICENSE
pysigrok_saleae_logic2-0.0.2.dist-info/WHEEL
pysigrok_saleae_logic2-0.0.2.dist-info/METADATA
pysigrok_saleae_logic2-0.0.2.dist-info/RECORD
