Metadata-Version: 2.1
Name: pysigrok-saleae-logic2
Version: 0.0.2
Summary: PySigrok driver for Saleae Logic 2 exports
Author-email: Scott Shawcroft <scott@tannewt.org>
Requires-Python: >=3.7
Classifier: License :: OSI Approved :: MIT License
Requires-Dist: pysigrok >= 0.4.0
Project-URL: Home, https://github.com/pysigrok/saleae-logic2
